utils/__init__.py
UnstructuredCDM-0.0.1.dist-info/METADATA
UnstructuredCDM-0.0.1.dist-info/WHEEL
UnstructuredCDM-0.0.1.dist-info/top_level.txt
UnstructuredCDM-0.0.1.dist-info/RECORD
