Metadata-Version: 2.1
Name: UnstructuredCDM
Version: 0.0.1
Summary: ODHSI CDM intergation package about unstructured medical data(radiology, XML, pathology...)
Home-page: https://github.com/ABMI/UnstructuredCDM
Author: Byungjin Choi
Author-email: choi328328@ajou.ac.kr
License: Apache
Platform: UNKNOWN
Requires-Python: >=3
